femtoqueue.py
femtoqueue-0.4.2.dist-info/licenses/LICENSE
femtoqueue-0.4.2.dist-info/METADATA
femtoqueue-0.4.2.dist-info/WHEEL
femtoqueue-0.4.2.dist-info/top_level.txt
femtoqueue-0.4.2.dist-info/RECORD
