Metadata-Version: 2.4
Name: femtoqueue
Version: 0.4.2
Summary: Ever wanted a zero-dependency, filesystem-backed, lock-free, durable, concurrent, retrying task queue implementation? No?
Author-email: Jan Tuomi <jan@jantuomi.fi>, Panu Oksiala <panu@oksiala.fi>
License-Expression: Apache-2.0
Project-URL: Homepage, https://github.com/jantuomi/femtoqueue
Project-URL: Issues, https://github.com/jantuomi/femtoqueue/issues
Classifier: Programming Language :: Python :: 3
Classifier: Operating System :: OS Independent
Requires-Python: >=3.10
License-File: LICENSE
Dynamic: license-file
